{"activities":[{"action":"uuid:fc40ad0a-ad84-468d-a98f-53d3e1fcab21::PunktLangsLinjeActivity","category":"Geometri-verktøy","description":"Verktøy som deler opp en linje i flere punkter.","displayName":"Del opp linje","inputs":{"geometri":{"description":"Input geometri i ArcGIS format.","displayName":"ArcGis Geometri","isRequired":true,"name":"geometri","typeName":"Polyline"},"avstand":{"description":"Avstanden mellom hvert punkt langs linje.","displayName":"Avstandsintervall","name":"avstand","typeName":"number"}},"outputs":{"result":{"description":"Resultatet av aktiviteten. \"error\" parameter viser bool-verdi om suksess eler ikke. Offset geometri finnes i \"offset\" parameter.","displayName":"Result","name":"result","typeName":"object"}},"suite":"uuid:fc40ad0a-ad84-468d-a98f-53d3e1fcab21"},{"action":"uuid:fc40ad0a-ad84-468d-a98f-53d3e1fcab21::SkalerGeometriActivity","category":"Geometri-verktøy","description":"skalerer geometri","displayName":"SkalerGeometri","inputs":{"geometri":{"description":"Input geometri i ArcGIS format.","displayName":"ArcGis Geometri","isRequired":true,"name":"geometri","typeName":"Geometry"},"avstand":{"description":"Input attributter.","displayName":"Avstand","name":"avstand","typeName":"number"}},"outputs":{"result":{"description":"The result of the activity.","displayName":"Result","name":"result","typeName":"object"}},"suite":"uuid:fc40ad0a-ad84-468d-a98f-53d3e1fcab21"},{"action":"uuid:fc40ad0a-ad84-468d-a98f-53d3e1fcab21::Kopier_tekstActivity","category":"Diverse verktøy","description":"En aktivitet som kopierer en tekststreng til utklippstavla","displayName":"Kopier tekst","inputs":{"tekst":{"description":"Tekst som skal kopieres til utklippstavla.","displayName":"Tekst","isRequired":true,"name":"tekst","typeName":"string"}},"outputs":{"result":{"description":"Resultatet av aktiviteten.","displayName":"Result","name":"result","typeName":"object"}},"suite":"uuid:fc40ad0a-ad84-468d-a98f-53d3e1fcab21"},{"action":"uuid:fc40ad0a-ad84-468d-a98f-53d3e1fcab21::DissolveActivity","category":"Geometri-verktøy","description":"Verktøy som slår sammen flater","displayName":"Dissolve","inputs":{"geometri":{"description":"En array med polygoner som skal slås sammen.","displayName":"Geometri","name":"geometri","typeName":"Array<Polygon>"},"features":{"description":"En array med features som skal slås sammen.","displayName":"Features","name":"features","typeName":"Array<__esri.Graphic>"},"egenskap":{"description":"Egenskapen som skal brukes til å slå sammen polygonene.","displayName":"Dissolve-egenskap","name":"egenskap","typeName":"string"}},"outputs":{"result":{"description":"The result of the activity.","displayName":"Result","name":"result","typeName":"object"}},"suite":"uuid:fc40ad0a-ad84-468d-a98f-53d3e1fcab21"},{"action":"uuid:fc40ad0a-ad84-468d-a98f-53d3e1fcab21::Vegsysref_punktActivity","category":"NVDB - verktøy","description":"En aktivitet som tar imot en vegsystemreferanse og dato og returnerer et koordinat","displayName":"Hent vegsystemreferanse - punkt","inputs":{"geometri":{"description":"En geometri som skal.","displayName":"Geomtri","isRequired":true,"name":"geometri","typeName":"Point"},"dato":{"description":"Hvilken dato skal vegsystemreferansen gjelde for.","displayName":"Dato","name":"dato","typeName":"Date"}},"outputs":{"result":{"description":"The result of the activity.","displayName":"Result","name":"result","typeName":"object"}},"suite":"uuid:fc40ad0a-ad84-468d-a98f-53d3e1fcab21"},{"action":"uuid:fc40ad0a-ad84-468d-a98f-53d3e1fcab21::SendWebRequestActivity","category":"Dataflyt","description":"En aktivitet for å konvertere sosi-data til features.","displayName":"Sosi2features","inputs":{"input1":{"description":"The file input to the activity.","displayName":"File Input","isRequired":true,"name":"input1","typeName":"File"},"input2":{"description":"The token for authentication.","displayName":"Token","isRequired":true,"name":"input2","typeName":"string"}},"outputs":{"result":{"description":"The result of the activity.","displayName":"Result","name":"result","typeName":"object"}},"suite":"uuid:fc40ad0a-ad84-468d-a98f-53d3e1fcab21"},{"action":"uuid:fc40ad0a-ad84-468d-a98f-53d3e1fcab21::NibioArealrapportActivity","category":"Beta","description":"En arealrapport for nibio","displayName":"NibioArealrapport","inputs":{"geometri":{"description":"Input geometri i ArcGIS format.","displayName":"ArcGis Geometri","isRequired":true,"name":"geometri","typeName":"object"},"srid":{"description":"Koordinatsystem for geom.","displayName":"Koordinatsystem","name":"srid","typeName":"number"}},"outputs":{"result":{"description":"The result of the activity.","displayName":"Result","name":"result","typeName":"object"}},"suite":"uuid:fc40ad0a-ad84-468d-a98f-53d3e1fcab21"},{"action":"uuid:fc40ad0a-ad84-468d-a98f-53d3e1fcab21::GruppelagActivity","category":"Kart-aktiviteter (SVV)","description":"En aktivitet som tar imot enkelt-lag og bygger det opp som et gruppelag","displayName":"Gruppelag","inputs":{"lag":{"description":"En array med lag som skal grupperes.","displayName":"Lag","isRequired":true,"name":"lag","typeName":"FeatureLayer[]"},"tittel":{"description":"Tittel på gruppelaget.","displayName":"Tittel  (valgfri)","name":"tittel","typeName":"string"}},"outputs":{"result":{"description":"The result of the activity.","displayName":"Result","name":"result","typeName":"GroupLayer"}},"suite":"uuid:fc40ad0a-ad84-468d-a98f-53d3e1fcab21"},{"action":"uuid:fc40ad0a-ad84-468d-a98f-53d3e1fcab21::ElevationLayerActivity","category":"Kart-aktiviteter (SVV)","description":"En aktivitet for å lage et hoyde-lag som kan legges til kartet","displayName":"ElevationLayer","inputs":{"url":{"description":"URL til høydelag","displayName":"URL","isRequired":true,"name":"url","typeName":"string"},"tittel":{"description":"Navn på laget","displayName":"Navn på lag","name":"tittel","typeName":"string"}},"outputs":{"result":{"description":"The result of the activity.","displayName":"Result","name":"result","typeName":"ElevationLayer"}},"suite":"uuid:fc40ad0a-ad84-468d-a98f-53d3e1fcab21"}],"elements":[]}